baldwin/__init__.py
baldwin/__main__.py
baldwin/lib.py
baldwin/main.py
baldwin/py.typed
baldwin/resources/default_gitattributes.txt
baldwin/resources/default_gitignore.txt
baldwin/resources/prettier.config.json
baldwin/typing.py
baldwin-0.0.10.dist-info/METADATA
baldwin-0.0.10.dist-info/WHEEL
baldwin-0.0.10.dist-info/entry_points.txt
baldwin-0.0.10.dist-info/licenses/LICENSE.txt
baldwin-0.0.10.dist-info/RECORD
