Metadata-Version: 2.4
Name: baldwin
Version: 0.0.10
Summary: Simple tracking of your home directory with easy-to-read diffs.
License-Expression: MIT
License-File: LICENSE.txt
Keywords: command line,file management,git,version control
Author: Andrew Udvare
Author-email: audvare@gmail.com
Requires-Python: >=3.10,<4.0
Classifier: Development Status :: 4 - Beta
Classifier: Intended Audience :: Developers
Classifier: Programming Language :: Python
Classifier: Programming Language :: Python :: 3.10
Classifier: Programming Language :: Python :: 3.11
Classifier: Programming Language :: Python :: 3.12
Classifier: Programming Language :: Python :: 3.13
Classifier: Programming Language :: Python :: 3.14
Classifier: Typing :: Typed
Requires-Dist: bascom (>=0.0.4,<0.0.5)
Requires-Dist: binaryornot (>=0.4.4,<0.5.0)
Requires-Dist: click (>=8.3.0,<9.0.0)
Requires-Dist: gitpython (>=3.1.45,<4.0.0)
Requires-Dist: platformdirs (>=4.5.0,<5.0.0)
Requires-Dist: tomlkit (>=0.13.3,<0.14.0)
Requires-Dist: typing-extensions (>=4.15.0,<5.0.0)
Project-URL: Documentation, https://baldwin.readthedocs.org
Project-URL: Homepage, https://tatsh.github.io/baldwin/
Project-URL: Issues, https://github.com/Tatsh/baldwin/issues
Project-URL: Repository, https://github.com/Tatsh/baldwin
